debug_context_manager.py
debug_context_manager-0.1.dist-info/DESCRIPTION.rst
debug_context_manager-0.1.dist-info/METADATA
debug_context_manager-0.1.dist-info/RECORD
debug_context_manager-0.1.dist-info/WHEEL
debug_context_manager-0.1.dist-info/metadata.json
debug_context_manager-0.1.dist-info/top_level.txt
