Metadata-Version: 2.0
Name: debug-context-manager
Version: 0.1
Summary: super simple context manager to print debug message
Home-page: https://github.com/Psycojoker/debug_context_manager
Author: Laurent Peuch
Author-email: cortex@worlddomination.be
License: MIT
Keywords: debug
Platform: UNKNOWN
